nimbus_post_office/__init__.py
nimbus_post_office/backends.py
nimbus_post_office/utils.py
nimbus_post_office-0.1.8.dist-info/LICENSE.md
nimbus_post_office-0.1.8.dist-info/METADATA
nimbus_post_office-0.1.8.dist-info/WHEEL
nimbus_post_office-0.1.8.dist-info/top_level.txt
nimbus_post_office-0.1.8.dist-info/RECORD
